{
  "last_updated": "2026-07-14 09:31:27 EDT",
  "data": {
    "SPY": {
      "today": {
        "date": "2026-07-14",
        "classic_dir": "Up",
        "classic_pct": 0.44,
        "classic_bucket": "<0.5%",
        "range_dir": null,
        "range_pct": 0.0,
        "range_bucket": null,
        "open": 752.47,
        "prev_close": 749.17,
        "prev_high": 753.91,
        "prev_low": 748.0
      },
      "stats": {
        "5Y": {
          "Classic": {
            "Up": {
              "<0.5%": {
                "total": 492,
                "filled": 359,
                "prob": 73.0
              },
              "0.5%-1%": {
                "total": 148,
                "filled": 56,
                "prob": 37.8
              },
              "1%-2%": {
                "total": 47,
                "filled": 16,
                "prob": 34.0
              },
              "2%-3%": {
                "total": 6,
                "filled": 0,
                "prob": 0.0
              },
              ">=3%": {
                "total": 3,
                "filled": 1,
                "prob": 33.3
              }
            },
            "Down": {
              "<0.5%": {
                "total": 376,
                "filled": 294,
                "prob": 78.2
              },
              "0.5%-1%": {
                "total": 110,
                "filled": 41,
                "prob": 37.3
              },
              "1%-2%": {
                "total": 62,
                "filled": 22,
                "prob": 35.5
              },
              "2%-3%": {
                "total": 8,
                "filled": 2,
                "prob": 25.0
              },
              ">=3%": {
                "total": 3,
                "filled": 1,
                "prob": 33.3
              }
            }
          },
          "Range": {
            "Up": {
              "<0.5%": {
                "total": 249,
                "filled": 203,
                "prob": 81.5
              },
              "0.5%-1%": {
                "total": 42,
                "filled": 16,
                "prob": 38.1
              },
              "1%-2%": {
                "total": 9,
                "filled": 3,
                "prob": 33.3
              },
              "2%-3%": {
                "total": 5,
                "filled": 0,
                "prob": 0.0
              },
              ">=3%": {
                "total": 0,
                "filled": 0,
                "prob": 0
              }
            },
            "Down": {
              "<0.5%": {
                "total": 129,
                "filled": 102,
                "prob": 79.1
              },
              "0.5%-1%": {
                "total": 44,
                "filled": 22,
                "prob": 50.0
              },
              "1%-2%": {
                "total": 15,
                "filled": 6,
                "prob": 40.0
              },
              "2%-3%": {
                "total": 3,
                "filled": 1,
                "prob": 33.3
              },
              ">=3%": {
                "total": 2,
                "filled": 1,
                "prob": 50.0
              }
            }
          }
        },
        "10Y": {
          "Classic": {
            "Up": {
              "<0.5%": {
                "total": 1042,
                "filled": 726,
                "prob": 69.7
              },
              "0.5%-1%": {
                "total": 281,
                "filled": 92,
                "prob": 32.7
              },
              "1%-2%": {
                "total": 90,
                "filled": 25,
                "prob": 27.8
              },
              "2%-3%": {
                "total": 13,
                "filled": 2,
                "prob": 15.4
              },
              ">=3%": {
                "total": 9,
                "filled": 3,
                "prob": 33.3
              }
            },
            "Down": {
              "<0.5%": {
                "total": 763,
                "filled": 586,
                "prob": 76.8
              },
              "0.5%-1%": {
                "total": 197,
                "filled": 75,
                "prob": 38.1
              },
              "1%-2%": {
                "total": 93,
                "filled": 35,
                "prob": 37.6
              },
              "2%-3%": {
                "total": 14,
                "filled": 5,
                "prob": 35.7
              },
              ">=3%": {
                "total": 11,
                "filled": 2,
                "prob": 18.2
              }
            }
          },
          "Range": {
            "Up": {
              "<0.5%": {
                "total": 573,
                "filled": 438,
                "prob": 76.4
              },
              "0.5%-1%": {
                "total": 85,
                "filled": 35,
                "prob": 41.2
              },
              "1%-2%": {
                "total": 17,
                "filled": 6,
                "prob": 35.3
              },
              "2%-3%": {
                "total": 10,
                "filled": 3,
                "prob": 30.0
              },
              ">=3%": {
                "total": 1,
                "filled": 0,
                "prob": 0.0
              }
            },
            "Down": {
              "<0.5%": {
                "total": 257,
                "filled": 209,
                "prob": 81.3
              },
              "0.5%-1%": {
                "total": 70,
                "filled": 35,
                "prob": 50.0
              },
              "1%-2%": {
                "total": 27,
                "filled": 12,
                "prob": 44.4
              },
              "2%-3%": {
                "total": 8,
                "filled": 4,
                "prob": 50.0
              },
              ">=3%": {
                "total": 5,
                "filled": 2,
                "prob": 40.0
              }
            }
          }
        },
        "30Y": {
          "Classic": {
            "Up": {
              "<0.5%": {
                "total": 3000,
                "filled": 2253,
                "prob": 75.1
              },
              "0.5%-1%": {
                "total": 879,
                "filled": 414,
                "prob": 47.1
              },
              "1%-2%": {
                "total": 283,
                "filled": 85,
                "prob": 30.0
              },
              "2%-3%": {
                "total": 49,
                "filled": 16,
                "prob": 32.7
              },
              ">=3%": {
                "total": 18,
                "filled": 5,
                "prob": 27.8
              }
            },
            "Down": {
              "<0.5%": {
                "total": 2333,
                "filled": 1860,
                "prob": 79.7
              },
              "0.5%-1%": {
                "total": 619,
                "filled": 291,
                "prob": 47.0
              },
              "1%-2%": {
                "total": 287,
                "filled": 115,
                "prob": 40.1
              },
              "2%-3%": {
                "total": 55,
                "filled": 23,
                "prob": 41.8
              },
              ">=3%": {
                "total": 22,
                "filled": 9,
                "prob": 40.9
              }
            }
          },
          "Range": {
            "Up": {
              "<0.5%": {
                "total": 1383,
                "filled": 1124,
                "prob": 81.3
              },
              "0.5%-1%": {
                "total": 252,
                "filled": 115,
                "prob": 45.6
              },
              "1%-2%": {
                "total": 70,
                "filled": 18,
                "prob": 25.7
              },
              "2%-3%": {
                "total": 18,
                "filled": 7,
                "prob": 38.9
              },
              ">=3%": {
                "total": 4,
                "filled": 2,
                "prob": 50.0
              }
            },
            "Down": {
              "<0.5%": {
                "total": 752,
                "filled": 631,
                "prob": 83.9
              },
              "0.5%-1%": {
                "total": 188,
                "filled": 115,
                "prob": 61.2
              },
              "1%-2%": {
                "total": 80,
                "filled": 44,
                "prob": 55.0
              },
              "2%-3%": {
                "total": 28,
                "filled": 19,
                "prob": 67.9
              },
              ">=3%": {
                "total": 10,
                "filled": 5,
                "prob": 50.0
              }
            }
          }
        }
      }
    },
    "QQQ": {
      "today": {
        "date": "2026-07-14",
        "classic_dir": "Up",
        "classic_pct": 1.18,
        "classic_bucket": "1%-2%",
        "range_dir": "Up",
        "range_pct": 0.19,
        "range_bucket": "<0.5%",
        "open": 720.14,
        "prev_close": 711.74,
        "prev_high": 718.74,
        "prev_low": 710.08
      },
      "stats": {
        "5Y": {
          "Classic": {
            "Up": {
              "<0.5%": {
                "total": 410,
                "filled": 309,
                "prob": 75.4
              },
              "0.5%-1%": {
                "total": 170,
                "filled": 84,
                "prob": 49.4
              },
              "1%-2%": {
                "total": 87,
                "filled": 22,
                "prob": 25.3
              },
              "2%-3%": {
                "total": 17,
                "filled": 5,
                "prob": 29.4
              },
              ">=3%": {
                "total": 6,
                "filled": 1,
                "prob": 16.7
              }
            },
            "Down": {
              "<0.5%": {
                "total": 312,
                "filled": 249,
                "prob": 79.8
              },
              "0.5%-1%": {
                "total": 149,
                "filled": 77,
                "prob": 51.7
              },
              "1%-2%": {
                "total": 89,
                "filled": 20,
                "prob": 22.5
              },
              "2%-3%": {
                "total": 8,
                "filled": 2,
                "prob": 25.0
              },
              ">=3%": {
                "total": 7,
                "filled": 2,
                "prob": 28.6
              }
            }
          },
          "Range": {
            "Up": {
              "<0.5%": {
                "total": 190,
                "filled": 155,
                "prob": 81.6
              },
              "0.5%-1%": {
                "total": 77,
                "filled": 43,
                "prob": 55.8
              },
              "1%-2%": {
                "total": 20,
                "filled": 4,
                "prob": 20.0
              },
              "2%-3%": {
                "total": 4,
                "filled": 1,
                "prob": 25.0
              },
              ">=3%": {
                "total": 3,
                "filled": 0,
                "prob": 0.0
              }
            },
            "Down": {
              "<0.5%": {
                "total": 113,
                "filled": 96,
                "prob": 85.0
              },
              "0.5%-1%": {
                "total": 43,
                "filled": 25,
                "prob": 58.1
              },
              "1%-2%": {
                "total": 27,
                "filled": 9,
                "prob": 33.3
              },
              "2%-3%": {
                "total": 6,
                "filled": 1,
                "prob": 16.7
              },
              ">=3%": {
                "total": 4,
                "filled": 2,
                "prob": 50.0
              }
            }
          }
        },
        "10Y": {
          "Classic": {
            "Up": {
              "<0.5%": {
                "total": 886,
                "filled": 653,
                "prob": 73.7
              },
              "0.5%-1%": {
                "total": 355,
                "filled": 155,
                "prob": 43.7
              },
              "1%-2%": {
                "total": 155,
                "filled": 41,
                "prob": 26.5
              },
              "2%-3%": {
                "total": 30,
                "filled": 8,
                "prob": 26.7
              },
              ">=3%": {
                "total": 12,
                "filled": 1,
                "prob": 8.3
              }
            },
            "Down": {
              "<0.5%": {
                "total": 645,
                "filled": 503,
                "prob": 78.0
              },
              "0.5%-1%": {
                "total": 253,
                "filled": 126,
                "prob": 49.8
              },
              "1%-2%": {
                "total": 138,
                "filled": 38,
                "prob": 27.5
              },
              "2%-3%": {
                "total": 23,
                "filled": 4,
                "prob": 17.4
              },
              ">=3%": {
                "total": 16,
                "filled": 3,
                "prob": 18.8
              }
            }
          },
          "Range": {
            "Up": {
              "<0.5%": {
                "total": 470,
                "filled": 362,
                "prob": 77.0
              },
              "0.5%-1%": {
                "total": 139,
                "filled": 69,
                "prob": 49.6
              },
              "1%-2%": {
                "total": 44,
                "filled": 16,
                "prob": 36.4
              },
              "2%-3%": {
                "total": 7,
                "filled": 2,
                "prob": 28.6
              },
              ">=3%": {
                "total": 4,
                "filled": 0,
                "prob": 0.0
              }
            },
            "Down": {
              "<0.5%": {
                "total": 217,
                "filled": 183,
                "prob": 84.3
              },
              "0.5%-1%": {
                "total": 77,
                "filled": 42,
                "prob": 54.5
              },
              "1%-2%": {
                "total": 47,
                "filled": 21,
                "prob": 44.7
              },
              "2%-3%": {
                "total": 10,
                "filled": 3,
                "prob": 30.0
              },
              ">=3%": {
                "total": 8,
                "filled": 3,
                "prob": 37.5
              }
            }
          }
        },
        "30Y": {
          "Classic": {
            "Up": {
              "<0.5%": {
                "total": 2326,
                "filled": 1818,
                "prob": 78.2
              },
              "0.5%-1%": {
                "total": 930,
                "filled": 488,
                "prob": 52.5
              },
              "1%-2%": {
                "total": 452,
                "filled": 181,
                "prob": 40.0
              },
              "2%-3%": {
                "total": 96,
                "filled": 29,
                "prob": 30.2
              },
              ">=3%": {
                "total": 42,
                "filled": 10,
                "prob": 23.8
              }
            },
            "Down": {
              "<0.5%": {
                "total": 1800,
                "filled": 1471,
                "prob": 81.7
              },
              "0.5%-1%": {
                "total": 685,
                "filled": 392,
                "prob": 57.2
              },
              "1%-2%": {
                "total": 419,
                "filled": 181,
                "prob": 43.2
              },
              "2%-3%": {
                "total": 83,
                "filled": 25,
                "prob": 30.1
              },
              ">=3%": {
                "total": 41,
                "filled": 11,
                "prob": 26.8
              }
            }
          },
          "Range": {
            "Up": {
              "<0.5%": {
                "total": 1051,
                "filled": 844,
                "prob": 80.3
              },
              "0.5%-1%": {
                "total": 306,
                "filled": 156,
                "prob": 51.0
              },
              "1%-2%": {
                "total": 128,
                "filled": 47,
                "prob": 36.7
              },
              "2%-3%": {
                "total": 23,
                "filled": 7,
                "prob": 30.4
              },
              ">=3%": {
                "total": 12,
                "filled": 4,
                "prob": 33.3
              }
            },
            "Down": {
              "<0.5%": {
                "total": 562,
                "filled": 488,
                "prob": 86.8
              },
              "0.5%-1%": {
                "total": 198,
                "filled": 116,
                "prob": 58.6
              },
              "1%-2%": {
                "total": 124,
                "filled": 63,
                "prob": 50.8
              },
              "2%-3%": {
                "total": 30,
                "filled": 11,
                "prob": 36.7
              },
              ">=3%": {
                "total": 17,
                "filled": 8,
                "prob": 47.1
              }
            }
          }
        }
      }
    }
  }
}